[
    {
        "id": 1,
        "title": "Comfortable",
        "launchYear": "2019",
        "favorited": true,
        "artists": [
            "H.E.R"
        ]
    },
    {
        "id": 2,
        "title": "Flawless",
        "launchYear": "2014",
        "favorited": true,
        "artists": [
            "Beyonce",
            "Nicki Minaj"
        ]
    },
    {
        "id": 3,
        "title": "Watercolor Eyes",
        "launchYear": "2022",
        "favorited": true,
        "artists": [
            "Lana Del Rey"
        ]
    },
    {
        "id": 4,
        "title": "Joro",
        "launchYear": "2019",
        "favorited": true,
        "artists": [
            "WizKid"
        ]
    },
    {
        "id": 5,
        "title": "Ghetto Love",
        "launchYear": "2019",
        "favorited": true,
        "artists": [
            "WizKid"
        ]
    },
    {
        "id": 6,
        "title": "Na sua estante",
        "launchYear": "2005",
        "favorited": true,
        "artists": [
            "Pitty"
        ]
    },
    {
        "id": 7,
        "title": "After the Storm",
        "launchYear": "2018",
        "favorited": true,
        "artists": [
            "Kali Uchis",
            "Tyler, The Creator",
            "Bootsy Collins"
        ]
    },
    {
        "id": 8,
        "title": "KEYS TO THE KINGDOM",
        "launchYear": "2020",
        "favorited": true,
        "artists": [
            "Tiwa Savage",
            "Mr. Eazi"
        ]
    },
    {
        "id": 9,
        "title": "Zero",
        "launchYear": "2015",
        "favorited": true,
        "artists": [
            "Liniker"
        ]
    },
    {
        "id": 10,
        "title": "Peligrosa",
        "launchYear": "2022",
        "favorited": true,
        "artists": [
            "Urias"
        ]
    },
    {
        "id": 11,
        "title": "Dangerous woman",
        "launchYear": "2016",
        "favorited": true,
        "artists": [
            "Ariana Grande"
        ]
    },
    {
        "id": 12,
        "title": "Sorry",
        "launchYear": "2016",
        "favorited": true,
        "artists": [
            "Beyonce"
        ]
    },
    {
        "id": 13,
        "title": "Modo turbo",
        "launchYear": "2021",
        "favorited": true,
        "artists": [
            "Luisa Sonza",
            "Anitta",
            "Pablo Vittar"
        ]
    },
    {
        "id": 14,
        "title": "Amor de que",
        "launchYear": "2020",
        "favorited": true,
        "artists": [
            "Pablo Vittar"
        ]
    },
    {
        "id": 15,
        "title": "te pongo mal(prendelo)",
        "launchYear": "2020",
        "favorited": true,
        "artists": [
            "Kali Uchis",
            "Jowell & Randy"
        ]
    },
    {
        "id": 16,
        "title": "Varias queixas",
        "launchYear": "2019",
        "favorited": true,
        "artists": [
            "Gilsons"
        ]
    },
    {
        "id": 17,
        "title": "Please me",
        "launchYear": "2019",
        "favorited": true,
        "artists": [
            "Cardi B",
            "Bruno Mars"
        ]
    },
    {
        "id": 18,
        "title": "Lili",
        "launchYear": "2021",
        "favorited": true,
        "artists": [
            "Liniker"
        ]
    },
    {
        "id": 19,
        "title": "Se Avexe Não",
        "launchYear": "2016",
        "favorited": true,
        "artists": [
            "Tassia Reis"
        ]
    }
]